[
    {
        "path": "poster",
        "description": "Drawn by venado_x",
        "title": "art super cool",
        "link": "https://www.instagram.com/venado_x?utm_source=ig_web_button_share_sheet&igsh=ZDNlZDc0MzIxNw=="
    },
    {
        "path": "culto",
        "description": "???",
        "title": "********",
        "link": ""
    },
    {
        "path": "shop",
        "description": "",
        "title": "shop concept discard",
        "link": ""  
    },
    {
        "path": "shop old",
        "description": "",
        "title": "shop old",
        "link": ""
    },
    {
        "path": "logo",
        "description": "",
        "title": "logo 1/2",
        "link": ""
    },
    {
        "path": "story_board-1",
        "description": "cinematica descartada por flojera",
        "title": "story_board-1",
        "link": ""
    },
    {
        "path": "story_board-2",
        "description": "",
        "title": "story_board-2",
        "link": ""
    },
    {
        "path": "story_board-3",
        "description": "",
        "title": "story_board-3",
        "link": ""
    },
    {
        "path": "band old",
        "description": "diceño antiguo de band (no mejoro mucho xdxd)",
        "title": "band old",
        "link": ""
    },
    {
        "path": "band old v2",
        "description": "",
        "title": "band old v2",
        "link": ""
    },
    {
        "path": "band kpro",
        "description": "no me acordaba de esto XD",
        "title": "band kpro",
        "link": ""
    },
    {
        "path": "dimon old",
        "description": "esta mrd son muy viejas este mod ya tiene como 3 años aunque esta version 4 meses",
        "title": "dimon old",
        "link": ""
    },
    {
        "path": "dimon bg og",
        "description": "",
        "title": "dimon bg old",
        "link": ""
    },
    {
        "path": "menu old1",
        "description": "",
        "title": "menu old1",
        "link": ""
    },
    {
        "path": "menu old2",
        "description": "",
        "title": "menu old2",
        "link": ""
    },
    {
        "path": "poster old",
        "description": "",
        "title": "poster old",
        "link": ""
    },
    {
        "path": "minion",
        "description": "jaja nose lol",
        "title": "minion",
        "link": ""
    },
    {
        "path": "sul old",
        "description": "pinche puta ni parecia mujer (o demonio)",
        "title": "sul old",
        "link": ""
    },
    {
        "path": "magic",
        "description": "oc que comparto con un amigo pero dudo que el se acuerde de el xdxd",
        "title": "magic",
        "link": ""
    },
    {
        "path": "bando",
        "description": "ser omnipresente que dibuje mientras cagaba",
        "title": "bando",
        "link": ""
    },
    {
        "path": "bando magic",
        "description": "crosover :0",
        "title": "bando magic",
        "link": ""
    }
]